kfpx/__init__.py
kfpx/client.py
kfpx-0.3.1.dist-info/METADATA
kfpx-0.3.1.dist-info/WHEEL
kfpx-0.3.1.dist-info/licenses/LICENSE
kfpx-0.3.1.dist-info/RECORD
