Metadata-Version: 2.1
Name: kfpx
Version: 0.3.1
Summary: Extends the kfp package
Author-email: Hao Xin <haoxinst@gmail.com>
License-File: LICENSE
Requires-Python: >=3.10
Requires-Dist: kfp==1.8.22
